[
  {
    "name": " CONcoin Crypto Prototype",
    "desc": " A fictitious cryptocurrency with a detailed website advertising physical and digital products.",
    "image" :"concoin",
    "category": "Web",
    "links": {
      "view": "https://joelmoyal.github.io/ConCoin-Crypto-Prototype/",
      "code": "https://github.com/JoelMoyal/ConCoinCryptoPrototype"
    }
  },
  {
    "name": "Flappy clone",
    "desc": "Unity-based game based on Flappy Bird. Available on browser or desktop (Windows, macOS).",
    "image": "flappy-clone",
    "category": "Games",
    "links": {
      "Play": "https://play.unity.com/en/games/98aa4ce9-ef0c-4221-8c98-142e5b3b40da/flappy-clone",
      "code": "https://github.com/JoelMoyal/Flappy-Clone"
    }
  },
  {
    "name": "Ticket System",
    "desc": "Ticket reservation service with integrated database, full end-to-end product",
    "image": "madlibs",
    "category": "Web",
    "links": {
      "view": "#",
      "code": "https://github.com/JoelMoyal/ticket-system"
    }
  },
  {
    "name": "Password Generator",
    "desc": "A modern, multilingual, client-side password generator that creates strong, secure passwords with customizable options.",
    "image": "pawg",
    "category": "Snippets",
    "links": {
      "view": "https://pwasecurity.org/",
      "code": "https://github.com/JoelMoyal/Password-generator"
    }
  },
  {
    "name": "Calendar in C",
    "desc": "A calendar program in C that empowers users to select any year and effortlessly visualizes the corresponding calendar.",
    "image": "calendar",
    "category": "Snippets",
    "links": {
      "code": "https://github.com/JoelMoyal/calendar-C"
    }
  },
  {
    "name": "My Portfolio",
    "desc": "Portfolio Website to showcase my projects, written in javascript, html, css.",
    "image": "portfolio",
    "category": "Web",
    "links": {
      "view": "#",
      "code": "#"
    }
  },
  {
    "name": "Food Counter",
    "desc": "Persistent data learning project using cloud database.",
    "image": "ticket_system",
    "category": "Web",
    "links": {
      "view": "https://github.com/JoelMoyal/food-counter",
      "code": "https://github.com/JoelMoyal/food-counter"
    }
  },
  {
    "name": "Bürgerbautrupp",
    "desc": "The NGO Village Project website, managed by me, documents projects, provides event details, fosters community involvement, and ensures legal compliance.",
    "image": "buergerbautrupp",
    "category": "Web",
    "links": {
      "view": "http://www.xn--brgerbautrupp-wob.de/",
      "code": "https://github.com/JoelMoyal/Buergerbautrupp"
    }
  },
  {
    "name": "Calculator",
    "desc": "Fully functional 4-function calculator programmed in C",
    "image": "calculator",
    "category": "Snippets",
    "links": {
      "view": "#",
      "code": "https://github.com/JoelMoyal/Calculator-C"
    }
  },

  {
    "name": "Mad Libs Game with C",
    "desc": "A barebones Mad Libs game in C as a learning project.",
    "image": "madlibs",
    "category": "Snippets",
    "links": {
      "code": "https://github.com/JoelMoyal/MadLibsGame"
    }
  },
  {
    "name": "Guessing Game",
    "desc": "A C-based game where a user guesses the correct number within the range of 0 to 15 in three attempts.",
    "image": "guessing",
    "category": "Snippets",
    "links": {
      "code": "https://github.com/JoelMoyal/guessing-Game"
    }
  },

{
  "name": "Simple Calculator in C",
  "desc": "A basic calculator using C that performs addition and subtraction functions.",
  "image": "calculator2",
  "category": "Snippets",
  "links": {
   "view": "",
    "code": "https://github.com/JoelMoyal/Simple-Calculator-C"
  }
},
{
  "name": "Rocketlight",
  "desc": "Digital corperate 3D designs for imaginary company using Blender and Adobe.",
  "image": "rocketlight",
  "category": "designs",
  "links": {
    "view": "https://www.behance.net/gallery/195828105/Rocketlight"
  }
},

  {
    "name": "Limetless",
    "desc": "A Futuristic Magazine created in Adobe InDesign and Adobe Illustrator.",
    "image": "catalog",
    "category": "designs",
    "links": {
      "view": " https://www.behance.net/gallery/194495239/Future-Magazine "
    }
  },
  {
    "name": "Flamenco Hotel Design",
    "desc": "The project cleverly integrates a graceful flamingo and prestigious hotel stars on a business card, effectively communicating the luxury brand's elegance and exclusivity.",
    "image": "Card",
    "category": "designs",
    "links": {
      "view": "https://www.behance.net/gallery/195806893/Flamingo-Hotel"
    }
  },
  {
    "name": "Advertisment",
    "desc": "Advertising without Image and Colour",
    "image": "Advertisment",
    "category": "designs",
    "links": {
      "view": "https://www.behance.net/gallery/195535217/Billboard-Advertising"
    }
  },
  {
    "name": "Photograph",
    "desc": "A Glimpse Through My Lens: A Journey Through the World of Photography",
    "image": "Photograph",
    "category": "designs",
    "links": {
      "view": "https://www.behance.net/gallery/195795697/A-Glimpse-Through-My-Lens"
    }
  },
  {
    "name": "Trettman Website",
    "desc": "A project to learn to create websites with guidance from W3Schools.",
    "image": "trettman",
    "category": "Web",
    "links": {
      "code": "https://github.com/JoelMoyal/Trettman-website"
    }
  }
  
]